track_duplicates/__init__.py
track_duplicates/__main__.py
track_duplicates/_version.py
track_duplicates/defaults.py
track_duplicates/lib.py
track_duplicates/utils.py
track_duplicates-0.0.1.dist-info/LICENSE
track_duplicates-0.0.1.dist-info/METADATA
track_duplicates-0.0.1.dist-info/WHEEL
track_duplicates-0.0.1.dist-info/entry_points.txt
track_duplicates-0.0.1.dist-info/top_level.txt
track_duplicates-0.0.1.dist-info/RECORD
